[{"id":20,"title":"PAW Patrol: Phim Si\u00eau \u0110\u1eb3ng \u2013 PAW Patrol: The Mighty Movie","slug":"paw-patrol-phim-sieu-dang-\u2013-paw-patrol-the-mighty-movie","description":"PAW Patrol: Phim Si\u00eau \u0110\u1eb3ng \u2013 PAW Patrol: The Mighty Movie, PAW Patrol: The Mighty Movie 2023 Full\r\nM\u1ed9t m\u1ea3nh thi\u00ean th\u1ea1ch k\u1ef3 di\u1ec7u \u0111\u00e3 r\u01a1i xu\u1ed1ng Th\u00e0nh Ph\u1ed1 Phi\u00eau L\u01b0u, mang \u0111\u1ebfn si\u00eau n\u0103ng l\u1ef1c cho nh\u1eefng ch\u00fa c\u00fan PAW Patrol v\u00e0 bi\u1ebfn ch\u00fang th\u00e0nh Nh\u1eefng Ch\u00fa C\u00fan Quy\u1ec1n N\u0103ng.","status":1,"image":"paw-patrol-poster5496.paw-patrol-poster.jpg","category_id":3,"genre_id":7,"country_id":5,"firm_hot":1,"resolution":0,"subtitle":0,"ngaytao":"2023-11-18 01:39:20","ngaycapnhat":"2023-11-18 01:39:20","year":"2023","thoiluongphim":"99 ph\u00fat","trailer":"Ql_DDtbnFhg","episode":1,"category":{"id":3,"title":"Phim l\u1ebb m\u1edbi","description":"phim l\u1ebb m\u1edbi 123","status":1,"slug":"phim-le-moi"},"movie_genre":[{"id":5,"title":"h\u00e0nh \u0111\u1ed9ng","description":"H\u00e0nh \u0111\u1ed9ng 123","status":1,"slug":"hanh-dong","pivot":{"movie_id":20,"genre_id":5}},{"id":7,"title":"Ho\u1ea1t h\u00ecnh","description":"ho\u1ea1t h\u00ecnh","status":1,"slug":"hoat-hinh","pivot":{"movie_id":20,"genre_id":7}}],"country":{"id":5,"title":"M\u1ef9","description":"phim m\u1ef9","status":1,"slug":"my"},"genre":{"id":7,"title":"Ho\u1ea1t h\u00ecnh","description":"ho\u1ea1t h\u00ecnh","status":1,"slug":"hoat-hinh"}},{"id":19,"title":"KUNG FU PANDA: HI\u1ec6P S\u0128 R\u1ed2NG","slug":"kung-fu-panda-hiep-si-rong","description":"Po t\u1ed1t b\u1ee5ng c\u00f9ng c\u00e1c Hi\u1ec7p S\u0129 R\u1ed3ng chu du kh\u1eafp th\u1ebf gi\u1edbi \u0111\u1ec3 t\u00ecm nh\u1eefng v\u0169 kh\u00ed Tianshang huy\u1ec1n tho\u1ea1i. Nh\u01b0ng li\u1ec7u h\u1ecd c\u00f3 th\u1ec3 nhanh ch\u00e2n h\u01a1n c\u00e1c th\u1ebf l\u1ef1c x\u1ea5u xa?","status":1,"image":"Kung Fu Panda The Dragon Knight S03 202340285193.Kung Fu Panda The Dragon Knight S03 20234028.jpg","category_id":3,"genre_id":7,"country_id":5,"firm_hot":1,"resolution":0,"subtitle":1,"ngaytao":"2023-11-17 01:30:49","ngaycapnhat":"2023-11-17 03:15:38","year":null,"thoiluongphim":"120 ph\u00fat","trailer":"Aftg630D6X8","episode":1,"category":{"id":3,"title":"Phim l\u1ebb m\u1edbi","description":"phim l\u1ebb m\u1edbi 123","status":1,"slug":"phim-le-moi"},"movie_genre":[{"id":6,"title":"T\u00ecnh c\u1ea3m","description":"tinh cam","status":1,"slug":"tinh-cam","pivot":{"movie_id":19,"genre_id":6}},{"id":7,"title":"Ho\u1ea1t h\u00ecnh","description":"ho\u1ea1t h\u00ecnh","status":1,"slug":"hoat-hinh","pivot":{"movie_id":19,"genre_id":7}}],"country":{"id":5,"title":"M\u1ef9","description":"phim m\u1ef9","status":1,"slug":"my"},"genre":{"id":7,"title":"Ho\u1ea1t h\u00ecnh","description":"ho\u1ea1t h\u00ecnh","status":1,"slug":"hoat-hinh"}},{"id":18,"title":"K\u1eba KI\u1ebeN T\u1ea0O","slug":"ke-kien-tao","description":"Joshua, m\u1ed9t c\u1ef1u \u0111\u1eb7c v\u1ee5 \u0111ang \u0111au bu\u1ed3n tr\u01b0\u1edbc s\u1ef1 m\u1ea5t t\u00edch c\u1ee7a ng\u01b0\u1eddi v\u1ee3, \u0111\u01b0\u1ee3c thu\u00ea \u0111\u1ec3 ti\u00eau di\u1ec7t Creator, k\u1ebb \u0111\u00e3 \u0111\u1ee9ng sau ph\u00e1t tri\u1ec3n m\u1ed9t lo\u1ea1i v\u0169 kh\u00ed c\u00f3 s\u1ee9c m\u1ea1nh ch\u1ea5m d\u1ee9t m\u1ecdi cu\u1ed9c chi\u1ebfn v\u00e0 s\u1ef1 s\u1ed1ng c\u1ee7a to\u00e0n th\u1ec3 nh\u00e2n lo\u1ea1i. Joshua v\u00e0 nh\u00f3m \u0111\u1eb7c v\u1ee5 tinh nhu\u1ec7 \u0111\u00e3 l\u1ea7n theo d\u1ea5u v\u1ebft ti\u1ebfn v\u00e0o l\u00e3nh th\u1ed5 b\u1ecb A.I chi\u1ebfm \u0111\u00f3ng, ch\u1ec9 \u0111\u1ec3 kh\u00e1m ph\u00e1 ra v\u0169 kh\u00ed h\u1ee7y di\u1ec7t th\u1ebf gi\u1edbi m\u00e0 anh ta \u0111\u01b0\u1ee3c giao ti\u00eau di\u1ec7t l\u00e0 m\u1ed9t A.I d\u01b0\u1edbi h\u00ecnh h\u00e0i c\u1ee7a m\u1ed9t \u0111\u1ee9a tr\u1ebb.","status":1,"image":"The Creator59798643.The Creator5979.jpg","category_id":3,"genre_id":6,"country_id":5,"firm_hot":1,"resolution":0,"subtitle":0,"ngaytao":"2023-11-16 02:47:43","ngaycapnhat":"2023-11-17 01:44:20","year":"2023","thoiluongphim":"135 phut","trailer":"XMvMTmDYtyE","episode":1,"category":{"id":3,"title":"Phim l\u1ebb m\u1edbi","description":"phim l\u1ebb m\u1edbi 123","status":1,"slug":"phim-le-moi"},"movie_genre":[{"id":5,"title":"h\u00e0nh \u0111\u1ed9ng","description":"H\u00e0nh \u0111\u1ed9ng 123","status":1,"slug":"hanh-dong","pivot":{"movie_id":18,"genre_id":5}},{"id":6,"title":"T\u00ecnh c\u1ea3m","description":"tinh cam","status":1,"slug":"tinh-cam","pivot":{"movie_id":18,"genre_id":6}}],"country":{"id":5,"title":"M\u1ef9","description":"phim m\u1ef9","status":1,"slug":"my"},"genre":{"id":6,"title":"T\u00ecnh c\u1ea3m","description":"tinh cam","status":1,"slug":"tinh-cam"}},{"id":17,"title":"NHI\u1ec6M V\u1ee4 B\u1ea4T KH\u1ea2 THI 7: NGHI\u1ec6P B\u00c1O PH\u1ea6N 1","slug":"nhiem-vu-bat-kha-thi-7-nghiep-bao-phan-1","description":"Ethan Hunt v\u00e0 nh\u00f3m IMF c\u1ee7a anh ph\u1ea3i truy t\u00ecm m\u1ed9t v\u0169 kh\u00ed nguy hi\u1ec3m tr\u01b0\u1edbc khi n\u00f3 r\u01a1i v\u00e0o tay k\u1ebb x\u1ea5u.","status":1,"image":"Mission Impossible Dead Reckoning Part One65603794.Mission Impossible Dead Reckoning Part One6560.jpg","category_id":3,"genre_id":6,"country_id":4,"firm_hot":1,"resolution":2,"subtitle":1,"ngaytao":"2023-11-13 00:59:56","ngaycapnhat":"2023-11-17 03:27:06","year":"2023","thoiluongphim":"180 ph\u00fat","trailer":null,"episode":1,"category":{"id":3,"title":"Phim l\u1ebb m\u1edbi","description":"phim l\u1ebb m\u1edbi 123","status":1,"slug":"phim-le-moi"},"movie_genre":[{"id":5,"title":"h\u00e0nh \u0111\u1ed9ng","description":"H\u00e0nh \u0111\u1ed9ng 123","status":1,"slug":"hanh-dong","pivot":{"movie_id":17,"genre_id":5}},{"id":6,"title":"T\u00ecnh c\u1ea3m","description":"tinh cam","status":1,"slug":"tinh-cam","pivot":{"movie_id":17,"genre_id":6}}],"country":{"id":4,"title":"Vi\u1ec7t Nam","description":"Vi\u1ec7t Nam 123","status":1,"slug":"viet-nam"},"genre":{"id":6,"title":"T\u00ecnh c\u1ea3m","description":"tinh cam","status":1,"slug":"tinh-cam"}},{"id":16,"title":"LOKI PH\u1ea6N 2","slug":"loki-phan-2","description":"Nh\u00e2n v\u1eadt ph\u1ea3n di\u1ec7n \u0111\u1ed3ng b\u00f3ng Loki ti\u1ebfp t\u1ee5c vai tr\u00f2 Th\u1ea7n kh\u1ed1n n\u1ea1n trong lo\u1ea1t phim m\u1edbi di\u1ec5n ra sau c\u00e1c s\u1ef1 ki\u1ec7n c\u1ee7a \u201cAvengers: Endgame\u201d.","status":1,"image":"Loki S02 20232142855.Loki S02 2023214.jpg","category_id":3,"genre_id":5,"country_id":4,"firm_hot":1,"resolution":5,"subtitle":1,"ngaytao":null,"ngaycapnhat":"2023-11-15 13:31:53","year":"2023","thoiluongphim":"180 ph\u00fat","trailer":"vwSKatRviQo","episode":1,"category":{"id":3,"title":"Phim l\u1ebb m\u1edbi","description":"phim l\u1ebb m\u1edbi 123","status":1,"slug":"phim-le-moi"},"movie_genre":[],"country":{"id":4,"title":"Vi\u1ec7t Nam","description":"Vi\u1ec7t Nam 123","status":1,"slug":"viet-nam"},"genre":{"id":5,"title":"h\u00e0nh \u0111\u1ed9ng","description":"H\u00e0nh \u0111\u1ed9ng 123","status":1,"slug":"hanh-dong"}},{"id":12,"title":"\u0110\u1ea2O H\u1ea2I T\u1eb6C 4","slug":"dao-hai-tac-4","description":"\u0110\u1ea2O H\u1ea2I T\u1eb6Cfsdgfgd","status":1,"image":"gia-dinh-diep-vien-phan-2-106279437.gia-dinh-diep-vien-phan-2-10627.jpg","category_id":3,"genre_id":5,"country_id":4,"firm_hot":1,"resolution":0,"subtitle":0,"ngaytao":null,"ngaycapnhat":null,"year":null,"thoiluongphim":"","trailer":null,"episode":1,"category":{"id":3,"title":"Phim l\u1ebb m\u1edbi","description":"phim l\u1ebb m\u1edbi 123","status":1,"slug":"phim-le-moi"},"movie_genre":[],"country":{"id":4,"title":"Vi\u1ec7t Nam","description":"Vi\u1ec7t Nam 123","status":1,"slug":"viet-nam"},"genre":{"id":5,"title":"h\u00e0nh \u0111\u1ed9ng","description":"H\u00e0nh \u0111\u1ed9ng 123","status":1,"slug":"hanh-dong"}},{"id":11,"title":"\u0110\u1ea2O H\u1ea2I T\u1eb6C 3","slug":"dao-hai-tac-3","description":"\u0110\u1ea2O H\u1ea2I T\u1eb6C","status":1,"image":"dao-hai-tac-7183561.dao-hai-tac-718.jpg","category_id":3,"genre_id":7,"country_id":4,"firm_hot":1,"resolution":0,"subtitle":0,"ngaytao":null,"ngaycapnhat":"2023-11-17 17:04:21","year":null,"thoiluongphim":null,"trailer":null,"episode":8,"category":{"id":3,"title":"Phim l\u1ebb m\u1edbi","description":"phim l\u1ebb m\u1edbi 123","status":1,"slug":"phim-le-moi"},"movie_genre":[{"id":7,"title":"Ho\u1ea1t h\u00ecnh","description":"ho\u1ea1t h\u00ecnh","status":1,"slug":"hoat-hinh","pivot":{"movie_id":11,"genre_id":7}}],"country":{"id":4,"title":"Vi\u1ec7t Nam","description":"Vi\u1ec7t Nam 123","status":1,"slug":"viet-nam"},"genre":{"id":7,"title":"Ho\u1ea1t h\u00ecnh","description":"ho\u1ea1t h\u00ecnh","status":1,"slug":"hoat-hinh"}},{"id":10,"title":"\u0110\u1ea2O H\u1ea2I T\u1eb6C 2","slug":"dao-hai-tac-2","description":"\u0110\u1ea3o H\u1ea3i T\u1eb7c - One Piece l\u00e0 chuy\u1ec7n v\u1ec1 c\u1eadu b\u00e9 Monkey D. Luffy do \u0103n nh\u1ea7m Tr\u00e1i \u00c1c Qu\u1ef7, b\u1ecb bi\u1ebfn th\u00e0nh ng\u01b0\u1eddi cao su v\u00e0 s\u1ebd kh\u00f4ng bao gi\u1edd bi\u1ebft b\u01a1i. 10 n\u0103m sau s\u1ef1 vi\u1ec7c \u0111\u00f3, c\u1eadu r\u1eddi qu\u00ea m\u00ecnh v\u00e0 ki\u1ebfm \u0111\u1ee7 10 th\u00e0nh vi\u00ean \u0111\u1ec3 th\u00e0nh m\u1ed9t b\u0103ng h\u1ea3i t\u1eb7c, bi\u1ec7t hi\u1ec7u H\u1ea3i t\u1eb7c M\u0169 R\u01a1m. Khi \u0111\u00f3 c\u1ee7a phi\u00eau l\u01b0u t\u00ecm ki\u1ebfm kho b\u00e1u One Piece b\u1eaft \u0111\u1ea7u. Trong cu\u1ed9c phi\u00eau l\u01b0u t\u00ecm ki\u1ebfm One Piec","status":1,"image":"gia-dinh-diep-vien-phan-2-106271952.gia-dinh-diep-vien-phan-2-10627.jpg","category_id":3,"genre_id":5,"country_id":4,"firm_hot":1,"resolution":0,"subtitle":0,"ngaytao":null,"ngaycapnhat":null,"year":null,"thoiluongphim":"","trailer":null,"episode":1,"category":{"id":3,"title":"Phim l\u1ebb m\u1edbi","description":"phim l\u1ebb m\u1edbi 123","status":1,"slug":"phim-le-moi"},"movie_genre":[],"country":{"id":4,"title":"Vi\u1ec7t Nam","description":"Vi\u1ec7t Nam 123","status":1,"slug":"viet-nam"},"genre":{"id":5,"title":"h\u00e0nh \u0111\u1ed9ng","description":"H\u00e0nh \u0111\u1ed9ng 123","status":1,"slug":"hanh-dong"}},{"id":9,"title":"\u0110\u1ea2O H\u1ea2I T\u1eb6C","slug":"dao-hai-tac","description":"\u0110\u1ea3o H\u1ea3i T\u1eb7c - One Piece l\u00e0 chuy\u1ec7n v\u1ec1 c\u1eadu b\u00e9 Monkey D. Luffy do \u0103n nh\u1ea7m Tr\u00e1i \u00c1c Qu\u1ef7, b\u1ecb bi\u1ebfn th\u00e0nh ng\u01b0\u1eddi cao su v\u00e0 s\u1ebd kh\u00f4ng bao gi\u1edd bi\u1ebft b\u01a1i. 10 n\u0103m sau s\u1ef1 vi\u1ec7c \u0111\u00f3, c\u1eadu r\u1eddi qu\u00ea m\u00ecnh v\u00e0 ki\u1ebfm \u0111\u1ee7 10 th\u00e0nh vi\u00ean \u0111\u1ec3 th\u00e0nh m\u1ed9t b\u0103ng h\u1ea3i t\u1eb7c, bi\u1ec7t hi\u1ec7u H\u1ea3i t\u1eb7c M\u0169 R\u01a1m. Khi \u0111\u00f3 c\u1ee7a phi\u00eau l\u01b0u t\u00ecm ki\u1ebfm kho b\u00e1u One Piece b\u1eaft \u0111\u1ea7u. Trong cu\u1ed9c phi\u00eau l\u01b0u t\u00ecm ki\u1ebfm One Piece, b\u0103ng H\u1ea3i t\u1eb7c m\u0169 r\u01a1m ph\u1ea3i chi\u1ebfn \u0111\u1ea5u v\u1edbi nhi\u1ec1u b\u0103ng h\u1ea3i t\u1eb7c x\u1ea5u kh\u00e1c c\u0169ng mu\u1ed1n \u0111\u1ed9c chi\u1ebfm One Piece v\u00e0 H\u1ea3i qu\u00e2n c\u1ee7a Ch\u00ednh ph\u1ee7 mu\u1ed1n di\u1ec7t tr\u1eeb h\u1ea3i t\u1eb7c. B\u0103ng H\u1ea3i t\u1eb7c M\u0169 R\u01a1m ph\u1ea3i tr\u1ea3i qua bi\u1ebft bao nhi\u00eau kh\u00f3 kh\u0103n, kh\u00f4ng l\u00f9i b\u01b0\u1edbc v\u1edbi \u01b0\u1edbc m\u01a1 \"Tr\u1edf th\u00e0nh Vua H\u1ea3i T\u1eb7c v\u00e0 chi\u1ebfm \u0111\u01b0\u1ee3c kho b\u00e1u One Piece\".","status":1,"image":"dao-hai-tac-7189356.dao-hai-tac-718.jpg","category_id":3,"genre_id":5,"country_id":4,"firm_hot":1,"resolution":0,"subtitle":0,"ngaytao":null,"ngaycapnhat":null,"year":null,"thoiluongphim":"","trailer":null,"episode":1,"category":{"id":3,"title":"Phim l\u1ebb m\u1edbi","description":"phim l\u1ebb m\u1edbi 123","status":1,"slug":"phim-le-moi"},"movie_genre":[],"country":{"id":4,"title":"Vi\u1ec7t Nam","description":"Vi\u1ec7t Nam 123","status":1,"slug":"viet-nam"},"genre":{"id":5,"title":"h\u00e0nh \u0111\u1ed9ng","description":"H\u00e0nh \u0111\u1ed9ng 123","status":1,"slug":"hanh-dong"}}]